{
  "FX": {
    "title": "[USD/JPY] UP: Geopolitical Tensions and Strong US Consumer Confidence Support Bullish Outlook",
    "date": "2026-04-29 02:45",
    "genre": "FX",
    "target_pair": "USD/JPY",
    "prediction_direction": "UP",
    "recommended_broker": "xm-trading",
    "tldr_points": [
      "US consumer confidence beats forecasts, underpinning USD strength",
      "Geopolitical frictions heighten safe‑haven demand for JPY, yet risk‑off bias favors USD in short‑term",
      "Technical profile shows bullish bias with support at 158.50 and upside potential toward 162.00"
    ],
    "chart_image": "/images/market-analysis-fx.png",
    "excerpt": "USD/JPY bullish on strong US confidence, geopolitical risk, and technical support near 158.5.",
    "pair": "USD/JPY",
    "status": "BUY",
    "comment": "Bullish on strong US confidence, rate differential, and technical support at MA20.",
    "entry": "158.60",
    "tp": "161.00",
    "sl": "158.10",
    "reliability": "HIGH"
  },
  "STOCKS": {
    "title": "[S&P 500] UP: Fundamental Momentum Outweighs Tech Sell-Off",
    "date": "2026-04-29 02:49",
    "genre": "STOCKS",
    "target_pair": "S&P 500",
    "prediction_direction": "UP",
    "recommended_broker": "[]",
    "tldr_points": [
      "Coca-Cola earnings signal resilience amid macro uncertainty",
      "AI-driven tech sell-off creates dislocation in high-float tech",
      "Semiconductor weakness temporarily lowers volatility premium"
    ],
    "chart_image": "/images/market-analysis-stocks.png",
    "excerpt": "Fundamental strength in earnings and growth stocks supports S&P 500 despite tech headwinds.",
    "pair": "S&P 500",
    "status": "NEUTRAL",
    "comment": "Fundamental strength in earnings and growth stocks supports S&P 500 despite tech headwinds.",
    "entry": "---",
    "tp": "---",
    "sl": "---",
    "reliability": "MEDIUM"
  },
  "CRYPTO": {
    "title": "[BTC/USD] UP: Regulatory Tailwinds and Infrastructure Scaling Offset Near-Term Earnings Volatility",
    "date": "2026-04-29 02:51",
    "genre": "CRYPTO",
    "target_pair": "BTC/USD",
    "prediction_direction": "UP",
    "recommended_broker": "bybit",
    "tldr_points": [
      "CFTC-Polymarket discussions signal advancing US regulatory clarity for crypto derivatives",
      "Lightning Network upgrades and AI trading agents expand Bitcoin utility and retail order flow",
      "Institutional bullishness on crypto data centers offsets near-term earnings volatility at major players"
    ],
    "chart_image": "/images/market-analysis-crypto.png",
    "excerpt": "BTC/USD bullish on CFTC talks, Lightning scaling, and institutional infra bets despite Q1 earnings volatility.",
    "pair": "BTC/USD",
    "status": "BUY",
    "comment": "Cautiously bullish on CFTC regulatory talks, Lightning Network scaling, and institutional data center bullishness, pending technical data validation.",
    "entry": "Unknown",
    "tp": "Unknown",
    "sl": "Unknown",
    "reliability": "MEDIUM"
  }
}