{
  "FX": {
    "title": "[USD/JPY] UP: Risk-on Momentum and Strong Fed‑Fed Divergence",
    "date": "2026-04-25 17:50",
    "genre": "FX",
    "target_pair": "USD/JPY",
    "prediction_direction": "UP",
    "recommended_broker": "xm-trading",
    "tldr_points": [
      "Risk‑on rally lifts USD",
      "Fed‑SOR divergence supports USD",
      "Key support at 145.00 and 144.50"
    ],
    "chart_image": "/images/market-analysis-fx.png",
    "excerpt": "USD/JPY poised higher on risk‑on sentiment and Fed‑Fed divergence with 145.00 as crucial support.",
    "pair": "USD/JPY",
    "status": "BUY",
    "comment": "Strong risk‑on momentum and Fed‑BOJ yield divergence support an upward bias.",
    "entry": "145.10",
    "tp": "147.00",
    "sl": "143.80",
    "reliability": "HIGH"
  },
  "STOCKS": {
    "title": "[S&P 500] [UP] [Positive technical bias supported by macro resilience and earnings catalysts] (e.g. '[S&P 500] UP: AI Detects Support at MA20 as Fundamentals Turn Bullish')",
    "date": "2026-04-25 17:52",
    "genre": "STOCKS",
    "target_pair": "S&P 500",
    "prediction_direction": "UP",
    "recommended_broker": "[]",
    "tldr_points": [
      "Structural support aligned with 20-day moving average underpins near-term upside.",
      "Historical forecasting tool signals low crash probability amid pro-growth policy.",
      "Earnings upgrades in financials and selective sectors reinforce positive risk appetite."
    ],
    "chart_image": "/images/market-analysis-stocks.png",
    "excerpt": "S&P 500 maintains structural support with favorable macro and earnings catalysts reducing crash risk.",
    "pair": "S&P 500",
    "status": "BUY",
    "comment": "Technical support and macro resilience favor upside continuation with low crash probability.",
    "entry": "0.00",
    "tp": "0.00",
    "sl": "0.00",
    "reliability": "HIGH"
  },
  "CRYPTO": {
    "title": "[BTC/USD] DOWN: AI Detects Weakening Momentum Amid Regulatory Headwinds",
    "date": "2026-04-25 17:53",
    "genre": "CRYPTO",
    "target_pair": "BTC/USD",
    "prediction_direction": "DOWN",
    "recommended_broker": "bybit",
    "tldr_points": [
      "Regulatory clampdowns intensify risk",
      "Liquidity thinning observed across order books",
      "Technical indicators show overbought conditions"
    ],
    "chart_image": "/images/market-analysis-crypto.png",
    "excerpt": "Regulatory pressure and deteriorating order flow push BTC/USD lower; entry near $28.5k with tight risk.",
    "pair": "BTC/USD",
    "status": "SELL",
    "comment": "Regulatory headwinds and overbought momentum justify a short bias.",
    "entry": "28,500",
    "tp": "27,800",
    "sl": "29,250",
    "reliability": "MEDIUM"
  }
}