{
  "FX": {
    "title": "Countdown to 152.50? AI Analytics Identifies Target for USD/JPY Breakout",
    "date": "2026-04-01 18:01",
    "genre": "FX",
    "target_pair": "USD/JPY",
    "prediction_direction": "UP",
    "recommended_broker": "xm-trading",
    "tldr_points": [
      "BOJ's stagflation dilemma caps policy tightening, supporting JPY weakness",
      "Technical setup shows bullish momentum above MA20 with RSI at 61",
      "Key resistance at 152.50, breakout targets 153.20"
    ],
    "chart_image": "/images/market-analysis-fx.png",
    "excerpt": "BOJ policy constraints and technical momentum drive USD/JPY higher. Key resistance at 152.50.",
    "pair": "USD/JPY",
    "status": "BUY",
    "comment": "Bullish momentum above MA20 with BOJ policy constraints supporting JPY weakness.",
    "entry": "150.90",
    "tp": "152.50",
    "sl": "150.40",
    "reliability": "HIGH"
  },
  "STOCKS": {
    "title": "Countdown to 5300? Institutional Analytics Sets S&P 500 Target Amid Volatility Surge",
    "date": "2026-04-01 18:04",
    "genre": "STOCKS",
    "target_pair": "S&P 500",
    "prediction_direction": "FLAT",
    "recommended_broker": "Goldman Sachs",
    "tldr_points": [
      "Volatility spike indicates heightened risk; VIX elevated.",
      "Oil price decline provides tailwind for equities.",
      "Technical levels undisclosed; awaiting MA20/RSI confirmation."
    ],
    "chart_image": "/images/market-analysis-stocks.png",
    "excerpt": "S&P 500 faces mixed signals: volatility up, oil down, technicals unknown. Neutral stance advised; monitor MA20/RSI.",
    "pair": "S&P 500",
    "status": "NEUTRAL",
    "comment": "Insufficient technical data; awaiting MA20/RSI confirmation for directional bias.",
    "entry": "0.00",
    "tp": "0.00",
    "sl": "0.00",
    "reliability": "LOW"
  },
  "CRYPTO": {
    "title": "BTC/USD Tactical Breakdown: Institutional Positioning Ahead of Q2 Rebalance",
    "date": "2026-04-01 18:07",
    "genre": "CRYPTO",
    "target_pair": "BTC/USD",
    "prediction_direction": "UP",
    "recommended_broker": "bybit",
    "tldr_points": [
      "Post-Q1 24% correction establishes oversold baseline",
      "Institutional bond issuance signals structural demand",
      "Regulatory scrutiny creates volatility around stablecoin rails"
    ],
    "chart_image": "/images/market-analysis-crypto.png",
    "excerpt": "Oversold BTC poised for institutional-driven rebound amid new bond issuance and regulatory clarity catalysts.",
    "pair": "BTC/USD",
    "status": "BUY",
    "comment": "Oversold technical posture meets bullish institutional catalyst (NH bond issuance) for tactical mean reversion.",
    "entry": "65000.00",
    "tp": "72000.00",
    "sl": "61000.00",
    "reliability": "HIGH"
  }
}